mcmicroprep/__init__.py
mcmicroprep/companion_script.py
mcmicroprep/core.py
mcmicroprep/microscopes/__init__.py
mcmicroprep/microscopes/base.py
mcmicroprep/microscopes/olympus.py
mcmicroprep/microscopes/rarecyte.py
mcmicroprep/preparemcmicro.py
mcmicroprep/templates/common/base.config
mcmicroprep/templates/common/batch_submission.sh
mcmicroprep/templates/common/markers.csv
mcmicroprep/templates/common/mcmicro_template.sh
mcmicroprep/templates/params/olympus.yml
mcmicroprep/templates/params/rarecyte.yml
mcmicroprep/templates/params_base.yml
mcmicroprep-0.1.0.dist-info/METADATA
mcmicroprep-0.1.0.dist-info/WHEEL
mcmicroprep-0.1.0.dist-info/entry_points.txt
mcmicroprep-0.1.0.dist-info/RECORD
