Metadata-Version: 2.1
Name: mcmicroprep
Version: 0.1.0
Summary: 
Author: Ajit Johnson Nirmal
Author-email: ajitjohnson.n@gmail.com
Requires-Python: >=3.10,<4.0
Classifier: Programming Language :: Python :: 3
Classifier: Programming Language :: Python :: 3.10
Classifier: Programming Language :: Python :: 3.11
Requires-Dist: lxml (>=6.0.0,<7.0.0)
Requires-Dist: ome-types (>=0.6.1,<0.7.0)
Requires-Dist: pandas (>=2.3.1,<3.0.0)
Requires-Dist: pydantic (>=2.11.7,<3.0.0)
